RsCmwBluetoothSig/RsCmwBluetoothSig.py
RsCmwBluetoothSig/__init__.py
RsCmwBluetoothSig/enums.py
RsCmwBluetoothSig/repcap.py
RsCmwBluetoothSig/CustomFiles/__init__.py
RsCmwBluetoothSig/CustomFiles/events.py
RsCmwBluetoothSig/CustomFiles/reliability.py
RsCmwBluetoothSig/CustomFiles/utilities.py
RsCmwBluetoothSig/Implementations/Source.py
RsCmwBluetoothSig/Implementations/__init__.py
RsCmwBluetoothSig/Implementations/Call/HciCustom.py
RsCmwBluetoothSig/Implementations/Call/LowEnergy.py
RsCmwBluetoothSig/Implementations/Call/__init__.py
RsCmwBluetoothSig/Implementations/Call/Connection/Action.py
RsCmwBluetoothSig/Implementations/Call/Connection/Check.py
RsCmwBluetoothSig/Implementations/Call/Connection/__init__.py
RsCmwBluetoothSig/Implementations/Call/DtMode/EndTx.py
RsCmwBluetoothSig/Implementations/Call/DtMode/StartTx.py
RsCmwBluetoothSig/Implementations/Call/DtMode/__init__.py
RsCmwBluetoothSig/Implementations/Clean/Elogging.py
RsCmwBluetoothSig/Implementations/Clean/__init__.py
RsCmwBluetoothSig/Implementations/Configure/Audio.py
RsCmwBluetoothSig/Implementations/Configure/Delay.py
RsCmwBluetoothSig/Implementations/Configure/HwInterface.py
RsCmwBluetoothSig/Implementations/Configure/__init__.py
RsCmwBluetoothSig/Implementations/Configure/ComSettings/BaudRate.py
RsCmwBluetoothSig/Implementations/Configure/ComSettings/ComPort.py
RsCmwBluetoothSig/Implementations/Configure/ComSettings/Dbits.py
RsCmwBluetoothSig/Implementations/Configure/ComSettings/Ereset.py
RsCmwBluetoothSig/Implementations/Configure/ComSettings/Parity.py
RsCmwBluetoothSig/Implementations/Configure/ComSettings/Ports.py
RsCmwBluetoothSig/Implementations/Configure/ComSettings/Protocol.py
RsCmwBluetoothSig/Implementations/Configure/ComSettings/StopBits.py
RsCmwBluetoothSig/Implementations/Configure/ComSettings/__init__.py
RsCmwBluetoothSig/Implementations/Configure/Connection/Ainterval.py
RsCmwBluetoothSig/Implementations/Configure/Connection/BdAddress.py
RsCmwBluetoothSig-4.0.230.dist-info/METADATA
RsCmwBluetoothSig-4.0.230.dist-info/WHEEL
RsCmwBluetoothSig-4.0.230.dist-info/top_level.txt
RsCmwBluetoothSig-4.0.230.dist-info/RECORD
