Metadata-Version: 2.1
Name: RsCmwBluetoothSig
Version: 4.0.230
Summary: CMW Bluetooth Signaling Remote-control module
Author: Rohde & Schwarz GmbH & Co. KG
License: MIT
Classifier: License :: OSI Approved :: MIT License
Classifier: Intended Audience :: Developers
Classifier: Operating System :: Microsoft :: Windows
Classifier: Operating System :: POSIX :: Linux
Classifier: Operating System :: MacOS :: MacOS X
Classifier: Programming Language :: Python
Classifier: Programming Language :: Python :: 3
Classifier: Programming Language :: Python :: 3.8
Classifier: Programming Language :: Python :: 3.9
Classifier: Programming Language :: Python :: 3.10
Classifier: Programming Language :: Python :: 3.11
Classifier: Programming Language :: Python :: 3.12
Requires-Python: >=3.8
Requires-Dist: PyVisa >=1.13.0
Requires-Dist: typing-extensions >=4.0.0
